correctimport/__init__.py
correctimport/directory_finder.py
correctimport/run.py
correctimport-0.4.0.dist-info/WHEEL
correctimport-0.4.0.dist-info/METADATA
correctimport-0.4.0.dist-info/RECORD
