Metadata-Version: 2.1
Name: correctimport
Version: 0.4.0
Summary: Fixing the imports for packaging: importing directly
Author: Yashesh Dasari
Author-email: yasheshdasari@gmail.com
Requires-Python: >=3.8,<4.0
Classifier: Programming Language :: Python :: 3
Classifier: Programming Language :: Python :: 3.8
Classifier: Programming Language :: Python :: 3.9
Classifier: Programming Language :: Python :: 3.10
Classifier: Programming Language :: Python :: 3.11
Requires-Dist: pathsingleton (==0.1.0)
